pageleaf/__init__.py
pageleaf-0.0.1.dist-info/licenses/LICENSE
pageleaf-0.0.1.dist-info/METADATA
pageleaf-0.0.1.dist-info/WHEEL
pageleaf-0.0.1.dist-info/top_level.txt
pageleaf-0.0.1.dist-info/RECORD
