Metadata-Version: 2.4
Name: pageleaf
Version: 0.0.1
Summary: PageLeaf is a personal paper-reading assistant for researchers and developers.
Author: Anders Cui
License: MIT
Project-URL: Homepage, https://github.com/anderscui/pageleaf
Project-URL: Repository, https://github.com/anderscui/pageleaf
Classifier: Development Status :: 1 - Planning
Classifier: Intended Audience :: Developers
Classifier: Topic :: Scientific/Engineering :: Artificial Intelligence
Classifier: License :: OSI Approved :: MIT License
Classifier: Programming Language :: Python :: 3
Classifier: Programming Language :: Python :: 3 :: Only
Requires-Python: >=3.10
License-File: LICENSE
Dynamic: license-file
